mtbench/__init__.py
mtbench/dataset_meta.py
mtbench/download.py
mtbench/download_config.yaml
mtbench/graph_dataset.py
mtbench/ondisk_dataset_creator.py
mtbench/rdb_dataset.py
mtbench/table_loader.py
mtbench/table_writer.py
mtbench/version.py
mtbench/yaml_utils.py
mtbench-0.0.1.dist-info/METADATA
mtbench-0.0.1.dist-info/WHEEL
mtbench-0.0.1.dist-info/top_level.txt
mtbench-0.0.1.dist-info/RECORD
